airflow_commons/__init__.py
airflow_commons/argument_parser.py
airflow_commons/aws.py
airflow_commons/config_helper.py
airflow_commons/gcp.py
airflow_commons/logger.py
airflow_commons/mixpanel.py
airflow_commons/mysql.py
airflow_commons/salesforce.py
airflow_commons/internal/__init__.py
airflow_commons/internal/athena/__init__.py
airflow_commons/internal/athena/constants.py
airflow_commons/internal/athena/core.py
airflow_commons/internal/athena/query.py
airflow_commons/internal/bigquery/__init__.py
airflow_commons/internal/bigquery/auth.py
airflow_commons/internal/bigquery/constants.py
airflow_commons/internal/bigquery/core.py
airflow_commons/internal/bigquery/defaults.py
airflow_commons/internal/bigquery/query.py
airflow_commons/internal/mixpanel/__init__.py
airflow_commons/internal/mixpanel/auth.py
airflow_commons/internal/mixpanel/constants.py
airflow_commons/internal/mixpanel/defaults.py
airflow_commons/internal/mysql/__init__.py
airflow_commons/internal/mysql/auth.py
airflow_commons/internal/mysql/core.py
airflow_commons/internal/mysql/query_utils.py
airflow_commons/internal/salesforce/__init__.py
airflow_commons/internal/salesforce/auth.py
airflow_commons/internal/salesforce/constants.py
airflow_commons/internal/salesforce/defaults.py
airflow_commons/internal/salesforce/http_utils.py
airflow_commons/internal/storage/__init__.py
airflow_commons/internal/storage/auth.py
airflow_commons/internal/storage/core.py
airflow_commons/internal/util/__init__.py
airflow_commons/internal/util/file_utils.py
airflow_commons/internal/util/log_utils.py
airflow_commons/internal/util/time_utils.py
airflow_commons/resources/__init__.py
airflow_commons/resources/athena/__init__.py
airflow_commons/resources/athena/add_partition/add_partition_statement.sql
airflow_commons/resources/bigquery/__init__.py
airflow_commons/resources/bigquery/archive/delete_where_statement.sql
airflow_commons/resources/bigquery/archive/source_statement.sql
airflow_commons-0.0.92.dist-info/licenses/LICENSE
airflow_commons-0.0.92.dist-info/METADATA
airflow_commons-0.0.92.dist-info/WHEEL
airflow_commons-0.0.92.dist-info/top_level.txt
airflow_commons-0.0.92.dist-info/RECORD
