Metadata-Version: 2.4
Name: airflow-commons
Version: 0.0.92
Summary: Common functions for airflow
Home-page: https://github.com/migroscomtr/airflow-commons/
Author: Startup Heroes
Classifier: Development Status :: 1 - Planning
Classifier: Programming Language :: Python :: 3
Classifier: License :: OSI Approved :: MIT License
Classifier: Operating System :: OS Independent
License-File: LICENSE
Requires-Dist: pytz>=2025.2
Requires-Dist: datetime
Requires-Dist: google-cloud-bigquery==3.40.0
Requires-Dist: google-cloud-storage==3.7.0
Requires-Dist: pandas
Requires-Dist: sqlalchemy
Requires-Dist: pymysql
Requires-Dist: boto3==1.41.5
Requires-Dist: botocore==1.41.5
Requires-Dist: aiobotocore==2.26.0
Requires-Dist: pyyaml
Requires-Dist: s3fs==2025.12.0
Requires-Dist: s3transfer
Requires-Dist: pyarrow
Dynamic: author
Dynamic: classifier
Dynamic: description
Dynamic: description-content-type
Dynamic: home-page
Dynamic: license-file
Dynamic: requires-dist
Dynamic: summary
